pythonz/__init__.py
pythonz/__main__.py
pythonz/define.py
pythonz/downloader.py
pythonz/log.py
pythonz/util.py
pythonz/version.py
pythonz/commands/__init__.py
pythonz/commands/cleanup.py
pythonz/commands/help.py
pythonz/commands/install.py
pythonz/commands/list.py
pythonz/commands/locate.py
pythonz/commands/uninstall.py
pythonz/commands/update.py
pythonz/commands/version.py
pythonz/etc/bashrc
pythonz/etc/pythonz.fish
pythonz/etc/bash_completion.d/pythonz_completion.sh
pythonz/installer/__init__.py
pythonz/installer/pythoninstaller.py
pythonz/installer/pythonzinstaller.py
pythonz/installer/versions.py
pythonz/patches/all/common/patch-setup.py.diff
pythonz/patches/all/python24/patch-setup.py.diff
pythonz/patches/all/python25/patch-setup.py.diff
pythonz/patches/all/python25/patch-svnversion.patch
pythonz/patches/all/python26/patch-nosslv2-1.diff
pythonz/patches/all/python26/patch-nosslv2-2.diff
pythonz/patches/all/python26/patch-nosslv2-3.diff
pythonz/patches/all/python30/patch-nosslv2.diff
pythonz/patches/all/python30/patch-setup.py.diff
pythonz/patches/all/python32/patch-setup.py.diff
pythonz/patches/osx/python24/patch-Include-pyport.h
pythonz/patches/osx/python24/patch-Lib-cgi.py.diff
pythonz/patches/osx/python24/patch-Lib-site.py.diff
pythonz/patches/osx/python24/patch-Makefile.pre.in
pythonz/patches/osx/python24/patch-configure-badcflags.diff
pythonz/patches/osx/python24/patch-macosmodule.diff
pythonz/patches/osx/python24/patch-mactoolboxglue.diff
pythonz/patches/osx/python24/patch-pymactoolbox.diff
pythonz/patches/osx/python24/patch240-Mac-OSX-Makefile.in
pythonz/patches/osx/python24/patch240-configure
pythonz/patches/osx/python24/patch240-gestaltmodule.c.diff
pythonz/patches/osx/python24/patch240-setup.py.diff
pythonz/patches/osx/python24/patch240-sysconfig.py.diff
pythonz/patches/osx/python24/patch241-configure
pythonz/patches/osx/python24/patch244-Mac-OSX-Makefile.in
pythonz_bd-1.11.4.dist-info/DESCRIPTION.rst
pythonz_bd-1.11.4.dist-info/METADATA
pythonz_bd-1.11.4.dist-info/RECORD
pythonz_bd-1.11.4.dist-info/WHEEL
pythonz_bd-1.11.4.dist-info/entry_points.txt
pythonz_bd-1.11.4.dist-info/metadata.json
pythonz_bd-1.11.4.dist-info/top_level.txt
