Metadata-Version: 1.1
Name: pythonz-bd
Version: 1.11.4
Summary: Manage python installations in your system, berdario's shallow fork
Home-page: https://github.com/berdario/pythonz/tree/bd
Author: saghul
Author-email: saghul@gmail.com
License: MIT
Platform: UNKNOWN
Classifier: Development Status :: 5 - Production/Stable
Classifier: Intended Audience :: Developers
Classifier: License :: OSI Approved :: MIT License
Classifier: Topic :: Software Development :: Build Tools
Classifier: Programming Language :: Python :: 2.6
Classifier: Programming Language :: Python :: 2.7
Classifier: Programming Language :: Python :: 3
Classifier: Programming Language :: Python :: 3.1
Classifier: Programming Language :: Python :: 3.2
Classifier: Programming Language :: Python :: 3.3
